airflow_freespace/__init__.py
airflow_freespace/operators/__init__.py
airflow_freespace/operators/free_space_sensor.py
airflow_imaging_plugins-2.4.3.dist-info/DESCRIPTION.rst
airflow_imaging_plugins-2.4.3.dist-info/METADATA
airflow_imaging_plugins-2.4.3.dist-info/RECORD
airflow_imaging_plugins-2.4.3.dist-info/WHEEL
airflow_imaging_plugins-2.4.3.dist-info/metadata.json
airflow_imaging_plugins-2.4.3.dist-info/top_level.txt
airflow_pipeline/__init__.py
airflow_pipeline/pipelines.py
airflow_pipeline/operators/__init__.py
airflow_pipeline/operators/bash_pipeline_operator.py
airflow_pipeline/operators/docker_pipeline_operator.py
airflow_pipeline/operators/prepare_pipeline_operator.py
airflow_pipeline/operators/python_pipeline_operator.py
airflow_scan_folder/__init__.py
airflow_scan_folder/operators/__init__.py
airflow_scan_folder/operators/common.py
airflow_scan_folder/operators/scan_folder_operator.py
airflow_scan_folder/operators/scan_folder_pipeline_operator.py
airflow_spm/__init__.py
airflow_spm/errors.py
airflow_spm/operators/__init__.py
airflow_spm/operators/spm_operator.py
airflow_spm/operators/spm_pipeline_operator.py
