Metadata-Version: 2.0
Name: airflow-imaging-plugins
Version: 2.4.3
Summary: Airflow plugins to support Neuroimaging tasks.
Home-page: https://github.com/LREN-CHUV/airflow-imaging-plugins
Author: LREN CHUV
Author-email: ludovic.claude@chuv.ch
License: Apache License 2.0
Keywords: airflow mri provenance
Platform: UNKNOWN
Classifier: Development Status :: 4 - Beta
Classifier: Environment :: Plugins
Classifier: Intended Audience :: Developers
Classifier: Intended Audience :: Science/Research
Classifier: Operating System :: Unix
Classifier: License :: OSI Approved :: Apache Software License
Classifier: Topic :: Scientific/Engineering :: Bio-Informatics
Classifier: Programming Language :: Python :: 3 :: Only
Classifier: Programming Language :: Python :: 3.3
Classifier: Programming Language :: Python :: 3.4
Classifier: Programming Language :: Python :: 3.5
Classifier: Programming Language :: Python :: 3.6
Requires-Dist: apache-airflow (==1.8.2)
Requires-Dist: data-tracking (>=1.7.2)
